sximage/__init__.py
sximage/__main__.py
sximage/fpgacap.py
sximage/sximage.py
sximage-0.2.0.dist-info/METADATA
sximage-0.2.0.dist-info/WHEEL
sximage-0.2.0.dist-info/entry_points.txt
sximage-0.2.0.dist-info/top_level.txt
sximage-0.2.0.dist-info/RECORD
