Metadata-Version: 2.1
Name: sximage
Version: 0.2.0
Summary: StreamLogic SxImage Python utilities
Home-page: UNKNOWN
Author: StreamLogic, LLC
License: UNKNOWN
Platform: UNKNOWN
Classifier: Programming Language :: Python :: 3
Classifier: License :: OSI Approved :: MIT License
Classifier: Operating System :: OS Independent
Requires-Python: >=3.6
Requires-Dist: pyserial
Requires-Dist: numpy
Requires-Dist: opencv-python
